README.md
setup.cfg
setup.py
GLXClansKeeper/__init__.py
GLXClansKeeper/__main__.py
GLXClansKeeper/libs/Ansible.py
GLXClansKeeper/libs/Clan.py
GLXClansKeeper/libs/Interface.py
GLXClansKeeper/libs/Keeper.py
GLXClansKeeper/libs/__init__.py
galaxie_clans_keeper.egg-info/PKG-INFO
galaxie_clans_keeper.egg-info/SOURCES.txt
galaxie_clans_keeper.egg-info/dependency_links.txt
galaxie_clans_keeper.egg-info/entry_points.txt
galaxie_clans_keeper.egg-info/not-zip-safe
galaxie_clans_keeper.egg-info/requires.txt
galaxie_clans_keeper.egg-info/top_level.txt