Metadata-Version: 2.1
Name: galaxie-clans-keeper
Version: 0.2
Summary: Galaxie Clans Keeper is a TUI application based on GLXCurses ToolKit to manage a Galaxie-Clans Ansible collection
Home-page: https://gitlab.com/aurelien.maury/galaxie-clans-keeper
Author: Tuuux
Author-email: tuxa@rtnp.org
License: GNU GENERAL PUBLIC LICENSE Version 3
Platform: UNKNOWN
Classifier: Development Status :: 3 - Alpha
Classifier: Environment :: Console
Classifier: Intended Audience :: Developers
Classifier: License :: OSI Approved :: GNU General Public License v3 or later (GPLv3+)
Classifier: Topic :: Software Development :: Libraries :: Python Modules
Classifier: Programming Language :: Python
Classifier: Programming Language :: Python :: 3 :: Only
Classifier: Topic :: Software Development :: Libraries :: Python Modules
